setup.py
pybigcommerce/__init__.py
pybigcommerce/bigcommerce.py
pybigcommerce/connector.py
pybigcommerce.egg-info/PKG-INFO
pybigcommerce.egg-info/SOURCES.txt
pybigcommerce.egg-info/dependency_links.txt
pybigcommerce.egg-info/requires.txt
pybigcommerce.egg-info/top_level.txt
pybigcommerce/modules/__init__.py
pybigcommerce/modules/customers.py
pybigcommerce/modules/store_info.py
test/__init__.py
test/main_test.py